{
  "build_id": "5426e18dfdaf870fb6aae4547d029fb960694505",
  "files": {
    "main.js": [
      "chunk-F67JBPXJ.js"
    ],
    "deserializer.js": [],
    "island-artifactmodal.js": [
      "chunk-LBTWPFPW.js",
      "chunk-LF3BN6YR.js",
      "chunk-F67JBPXJ.js"
    ],
    "island-buggyinvestigationworksheet.js": [
      "chunk-LF3BN6YR.js",
      "chunk-F67JBPXJ.js"
    ],
    "island-googlesheetstutorial.js": [
      "chunk-LF3BN6YR.js",
      "chunk-F67JBPXJ.js"
    ],
    "island-mobilemenu.js": [
      "chunk-LF3BN6YR.js",
      "chunk-F67JBPXJ.js"
    ],
    "island-pdfmodal.js": [
      "chunk-LBTWPFPW.js",
      "chunk-LF3BN6YR.js",
      "chunk-F67JBPXJ.js"
    ],
    "chunk-LBTWPFPW.js": [
      "chunk-F67JBPXJ.js"
    ],
    "chunk-LF3BN6YR.js": [
      "chunk-F67JBPXJ.js"
    ],
    "chunk-F67JBPXJ.js": [],
    "metafile.json": []
  }
}